thatscrapper/__init__.py
thatscrapper/browser.py
thatscrapper/common/__init__.py
thatscrapper/common/exceptions.py
thatscrapper/common/logger.py
thatscrapper/data.py
thatscrapper/extractor.py
thatscrapper-0.1.0.dist-info/LICENSE
thatscrapper-0.1.0.dist-info/WHEEL
thatscrapper-0.1.0.dist-info/METADATA
thatscrapper-0.1.0.dist-info/RECORD
